jsonalize/__init__.py
jsonalize/jsonalize.py
jsonalize-0.2.dist-info/LICENSE
jsonalize-0.2.dist-info/METADATA
jsonalize-0.2.dist-info/WHEEL
jsonalize-0.2.dist-info/top_level.txt
jsonalize-0.2.dist-info/RECORD
