Metadata-Version: 2.1
Name: jsonalize
Version: 0.2
Summary: A JSON data binding library for Python
Home-page: https://github.com/nianxy/jsonalize
Author: Stanley Nian
Author-email: stanley.nian@yandex.com
License: UNKNOWN
Platform: any
Classifier: Programming Language :: Python :: 2.7
Classifier: Programming Language :: Python :: 3.7
Classifier: License :: OSI Approved :: MIT License
Classifier: Operating System :: OS Independent
Requires-Python: >=2.7
